svector/__init__.py
svector/immutable_list.py
svector/immutable_tree.py
svector/py.typed
svector/type_definitions.py
svector-0.1.1.dist-info/LICENSE
svector-0.1.1.dist-info/WHEEL
svector-0.1.1.dist-info/METADATA
svector-0.1.1.dist-info/RECORD
