Metadata-Version: 2.1
Name: svector
Version: 0.1.1
Summary: Typesafe immutable datastructure for python. With plenty of methods for fluent functional programming.
Home-page: https://github.com/thejaminator/svector
License: MIT
Author: James Chua
Author-email: chuajamessh@gmail.com
Requires-Python: >=3.9,<4.0
Classifier: Development Status :: 2 - Pre-Alpha
Classifier: Intended Audience :: Developers
Classifier: License :: OSI Approved :: MIT License
Classifier: Natural Language :: English
Classifier: Programming Language :: Python :: 3
Classifier: Programming Language :: Python :: 3.10
Classifier: Programming Language :: Python :: 3.6
Classifier: Programming Language :: Python :: 3.7
Classifier: Programming Language :: Python :: 3.8
Classifier: Programming Language :: Python :: 3.9
Provides-Extra: dev
Provides-Extra: doc
Provides-Extra: test
Requires-Dist: pyrsistent (>=0.17.0)
